mvp_msr8.py
mvp_msr8-0.1.4.dist-info/LICENSE.txt
mvp_msr8-0.1.4.dist-info/METADATA
mvp_msr8-0.1.4.dist-info/WHEEL
mvp_msr8-0.1.4.dist-info/entry_points.txt
mvp_msr8-0.1.4.dist-info/top_level.txt
mvp_msr8-0.1.4.dist-info/RECORD
